{"WCI-w1":{"required":[],"required_only":false},"WCI-w2":{"required":[],"required_only":false},"THURSDAY-Lab3-PostLab-Task1":{"required":[],"required_only":false},"FRIDAY-Lab3-PostLab-Task1":{"required":[],"required_only":false},"WCI-w3":{"required":[],"required_only":false},"A1":{"required":["INFO.txt","Kbuild","Makefile","plagiarism.txt","interceptor.h","interceptor.c"],"required_only":false},"THURSDAY-Lab3-PostLab-Task2":{"required":[],"required_only":false},"FRIDAY-Lab3-PostLab-Task2":{"required":[],"required_only":false},"WCI-w4":{"required":[],"required_only":false},"WCI-RW":{"required":[],"required_only":false},"A2":{"required":["executor.c","jobs.c","executor.h","Makefile","INFO.txt","plagiarism.txt"],"required_only":false},"WCI-w5":{"required":[],"required_only":false},"LE8":{"required":[],"required_only":false},"WCI-w6":{"required":[],"required_only":false},"WCI-w7":{"required":[],"required_only":false},"TE8":{"required":[],"required_only":false},"WCI-w8":{"required":[],"required_only":false},"A3":{"required":["arc.c","fifo.c","Makefile","INFO.txt","swap.c","rand.c","pagetable.h","clock.c","lru.c","sim.c","sim.h","pagetable.c","README.pdf","plagiarism.txt"],"required_only":false},"TE9":{"required":[],"required_only":false},"TE10":{"required":[],"required_only":false},"WCI-w9":{"required":[],"required_only":false},"A4":{"required":["plagiarism.txt","INFO.txt"],"required_only":false}}